{
  "文 本": 5,
  "t e": 6,
  "i n": 7,
  "r e": 8,
  "識 別": 9,
  "a n": 10,
  "o n": 11,
  "t i": 12,
  "o r": 13,
  "e n": 14,
  "學 習": 15,
  "in g": 16,
  "模 型": 17,
  "e s": 18,
  "e r": 19,
  "語 言": 20,
  "數 據": 21,
  "a r": 22,
  "ti on": 23,
  "a l": 24,
  "e l": 25,
  "t s": 26,
  "f or": 27,
  "r o": 28,
  "處 理": 29,
  "i s": 30,
  "m o": 31,
  "a s": 32,
  "實 體": 33,
  "文本 的": 34,
  "t h": 35,
  "u m": 36,
  "可 以": 37,
  "te x": 38,
  "tex t": 39,
  "l e": 40,
  "mo d": 41,
  "mod el": 42,
  "a t": 43,
  "e d": 44,
  "中 的": 45,
  "c a": 46,
  "表 達": 47,
  "轉 換": 48,
  "語 法": 49,
  "th e": 50,
  "q u": 51,
  "人 工": 52,
  "人工 智": 53,
  "人工智 能": 54,
  "a c": 55,
  "model s": 56,
  "t r": 57,
  "任 務": 58,
  "p ro": 59,
  "w or": 60,
  "te n": 61,
  "c es": 62,
  "n e": 63,
  "標 準": 64,
  "文本 中": 65,
  "關 係": 66,
  "確 定": 67,
  "檢 測": 68,
  "識別 和": 69,
  "l a": 70,
  "自 然": 71,
  "n ing": 72,
  "an s": 73,
  "t u": 74,
  "m p": 75,
  "系 統": 76,
  "詞 語": 77,
  "評 估": 78,
  "te r": 79,
  "a d": 80,
  "特 定": 81,
  "生 成": 82,
  "上 下": 83,
  "上下 文": 84,
  "s i": 85,
  "情 感": 86,
  "分 析": 87,
  "將 文本": 88,
  "c o": 89,
  "語 音": 90,
  "標 記": 91,
  "一 個": 92,
  "d o": 93,
  "自然 語言": 94,
  "技 術": 95,
  "le ar": 96,
  "lear ning": 97,
  "re qu": 98,
  "g e": 99,
  "圖 像": 100,
  "tr ans": 101,
  "for m": 102,
  "c h": 103,
  "tu re": 104
}